agentscope/__init__.py
agentscope/_logging.py
agentscope/_run_config.py
agentscope/_version.py
agentscope/py.typed
agentscope/_utils/__init__.py
agentscope/_utils/_common.py
agentscope/_utils/_mixin.py
agentscope/a2a/__init__.py
agentscope/a2a/_base.py
agentscope/a2a/_file_resolver.py
agentscope/a2a/_nacos_resolver.py
agentscope/a2a/_well_known_resolver.py
agentscope/agent/__init__.py
agentscope/agent/_a2a_agent.py
agentscope/agent/_agent_base.py
agentscope/agent/_agent_meta.py
agentscope/agent/_react_agent.py
agentscope/agent/_react_agent_base.py
agentscope/agent/_user_agent.py
agentscope/agent/_user_input.py
agentscope/agent/_utils.py
agentscope/embedding/__init__.py
agentscope/embedding/_cache_base.py
agentscope/embedding/_dashscope_embedding.py
agentscope/embedding/_dashscope_multimodal_embedding.py
agentscope/embedding/_embedding_base.py
agentscope/embedding/_embedding_response.py
agentscope/embedding/_embedding_usage.py
agentscope/embedding/_file_cache.py
agentscope/embedding/_gemini_embedding.py
agentscope/embedding/_ollama_embedding.py
agentscope/embedding/_openai_embedding.py
agentscope/evaluate/__init__.py
agentscope/evaluate/_benchmark_base.py
agentscope/evaluate/_metric_base.py
agentscope/evaluate/_solution.py
agentscope/evaluate/_task.py
agentscope/evaluate/_ace_benchmark/__init__.py
agentscope/evaluate/_ace_benchmark/_ace_benchmark.py
agentscope/evaluate/_ace_benchmark/_ace_metric.py
agentscope/evaluate/_ace_benchmark/_ace_tools_zh.py
agentscope/evaluate/_ace_benchmark/_ace_tools_api/__init__.py
agentscope/evaluate/_ace_benchmark/_ace_tools_api/_food_platform_api.py
agentscope/evaluate/_ace_benchmark/_ace_tools_api/_message_api.py
agentscope/evaluate/_ace_benchmark/_ace_tools_api/_reminder_api.py
agentscope/evaluate/_ace_benchmark/_ace_tools_api/_shared_state.py
agentscope/evaluate/_ace_benchmark/_ace_tools_api/_travel_api.py
agentscope/evaluate/_evaluator/__init__.py
agentscope/evaluate/_evaluator/_evaluator_base.py
agentscope-1.0.12.dist-info/licenses/LICENSE
agentscope-1.0.12.dist-info/METADATA
agentscope-1.0.12.dist-info/WHEEL
agentscope-1.0.12.dist-info/top_level.txt
agentscope-1.0.12.dist-info/RECORD
