Metadata-Version: 2.4
Name: agentscope
Version: 1.0.12
Summary: AgentScope: A Flexible yet Robust Multi-Agent Platform.
Author-email: SysML team of Alibaba Tongyi Lab <gaodawei.gdw@alibaba-inc.com>
License-Expression: Apache-2.0
Project-URL: Homepage, https://github.com/agentscope-ai/agentscope
Project-URL: Documentation, https://doc.agentscope.io/
Project-URL: Repository, https://github.com/agentscope-ai/agentscope
Keywords: deep-learning,multi agents,agents
Classifier: Development Status :: 4 - Beta
Classifier: Programming Language :: Python :: 3
Classifier: Programming Language :: Python :: 3.10
Classifier: Operating System :: OS Independent
Classifier: Intended Audience :: Developers
Classifier: Intended Audience :: Science/Research
Classifier: Topic :: Scientific/Engineering :: Artificial Intelligence
Requires-Python: >=3.10
License-File: LICENSE
Requires-Dist: aioitertools
Requires-Dist: anthropic
Requires-Dist: dashscope
Requires-Dist: docstring_parser
Requires-Dist: json5
Requires-Dist: json_repair
Requires-Dist: mcp>=1.13
Requires-Dist: numpy
Requires-Dist: openai
Requires-Dist: python-datauri
Requires-Dist: opentelemetry-api>=1.39.0
Requires-Dist: opentelemetry-sdk>=1.39.0
Requires-Dist: opentelemetry-exporter-otlp>=1.39.0
Requires-Dist: opentelemetry-semantic-conventions>=0.60b0
Requires-Dist: python-socketio
Requires-Dist: shortuuid
Requires-Dist: tiktoken
Requires-Dist: sounddevice
Requires-Dist: sqlalchemy
Requires-Dist: python-frontmatter
Provides-Extra: a2a
Requires-Dist: a2a-sdk; extra == "a2a"
Requires-Dist: httpx; extra == "a2a"
Requires-Dist: nacos-sdk-python>=3.0.0; extra == "a2a"
Provides-Extra: gemini
Requires-Dist: google-genai; extra == "gemini"
Provides-Extra: ollama
Requires-Dist: ollama>=0.5.4; extra == "ollama"
Provides-Extra: models
Requires-Dist: agentscope[ollama]; extra == "models"
Requires-Dist: agentscope[gemini]; extra == "models"
Provides-Extra: tokens
Requires-Dist: Pillow; extra == "tokens"
Requires-Dist: transformers; extra == "tokens"
Requires-Dist: jinja2; extra == "tokens"
Provides-Extra: redis-memory
Requires-Dist: redis; extra == "redis-memory"
Provides-Extra: mem0ai
Requires-Dist: mem0ai<=0.1.116; extra == "mem0ai"
Requires-Dist: packaging; extra == "mem0ai"
Provides-Extra: reme
Requires-Dist: reme-ai>=0.2.0.3; extra == "reme"
Provides-Extra: memory
Requires-Dist: agentscope[redis_memory]; extra == "memory"
Requires-Dist: agentscope[mem0ai]; extra == "memory"
Requires-Dist: agentscope[reme]; extra == "memory"
Provides-Extra: text-reader
Requires-Dist: nltk; extra == "text-reader"
Provides-Extra: pdf-reader
Requires-Dist: agentscope[text-reader]; extra == "pdf-reader"
Requires-Dist: pypdf<=6.5.0; extra == "pdf-reader"
Provides-Extra: docx-reader
Requires-Dist: agentscope[text-reader]; extra == "docx-reader"
Requires-Dist: python-docx; extra == "docx-reader"
Provides-Extra: readers
Requires-Dist: agentscope[text-reader]; extra == "readers"
Requires-Dist: agentscope[pdf-reader]; extra == "readers"
Requires-Dist: agentscope[docx-reader]; extra == "readers"
Provides-Extra: qdrant
Requires-Dist: qdrant-client==1.15.1; extra == "qdrant"
Provides-Extra: milvus
Requires-Dist: pymilvus[milvus_lite]; extra == "milvus"
Provides-Extra: ali-mysql
Requires-Dist: mysql-connector-python; extra == "ali-mysql"
Provides-Extra: vdbs
Requires-Dist: agentscope[ali_mysql]; extra == "vdbs"
Requires-Dist: agentscope[qdrant]; extra == "vdbs"
Requires-Dist: agentscope[milvus]; extra == "vdbs"
Provides-Extra: rag
Requires-Dist: agentscope[readers]; extra == "rag"
Requires-Dist: agentscope[vdbs]; extra == "rag"
Provides-Extra: evaluate
Requires-Dist: ray; extra == "evaluate"
Provides-Extra: full
Requires-Dist: agentscope[a2a]; extra == "full"
Requires-Dist: agentscope[models]; extra == "full"
Requires-Dist: agentscope[tokens]; extra == "full"
Requires-Dist: agentscope[memory]; extra == "full"
Requires-Dist: agentscope[rag]; extra == "full"
Requires-Dist: agentscope[evaluate]; extra == "full"
Provides-Extra: dev
Requires-Dist: agentscope[full]; extra == "dev"
Requires-Dist: pre-commit; extra == "dev"
Requires-Dist: pytest; extra == "dev"
Requires-Dist: pytest-forked; extra == "dev"
Requires-Dist: sphinx-gallery; extra == "dev"
Requires-Dist: furo; extra == "dev"
Requires-Dist: myst_parser; extra == "dev"
Requires-Dist: matplotlib; extra == "dev"
Requires-Dist: fakeredis; extra == "dev"
Requires-Dist: aiosqlite; extra == "dev"
Requires-Dist: greenlet; extra == "dev"
Dynamic: license-file
